tchart/__init__.py
tchart/decorators.py
tchart/renderers.py
tchart/tchart.py
tchart-2.0.0.dist-info/DESCRIPTION.rst
tchart-2.0.0.dist-info/METADATA
tchart-2.0.0.dist-info/RECORD
tchart-2.0.0.dist-info/WHEEL
tchart-2.0.0.dist-info/metadata.json
tchart-2.0.0.dist-info/pbr.json
tchart-2.0.0.dist-info/top_level.txt
