Metadata-Version: 2.0
Name: tchart
Version: 2.0.0
Summary: Minimal graph renderer for fixed size canvas
Home-page: https://github.com/andras-tim/tchart
Author: Andras Tim
Author-email: andras.tim@gmail.com
License: GPLv3
Keywords: chart bar barchart
Platform: any
Classifier: Development Status :: 5 - Production/Stable
Classifier: Intended Audience :: Developers
Classifier: Topic :: Scientific/Engineering :: Visualization
Classifier: License :: OSI Approved :: GNU General Public License v3 (GPLv3)
Classifier: Programming Language :: Python :: 2
Classifier: Programming Language :: Python :: 3
Requires-Dist: numpy
